[
  {
    "id": "b7299ea5-b979-4b0e-8e2c-ab9ddffa6137",
    "data": [
      {
        "text": "काफ़ी दिनों से बात नहीं हुई",
        "userDefined": false
      }
    ],
    "isTemplate": false,
    "count": 0,
    "lang": "hi",
    "updated": 0
  },
  {
    "id": "fe22bfae-3ff4-4a99-8737-6066f5dbf68c",
    "data": [
      {
        "text": "नमस्कार",
        "userDefined": false
      }
    ],
    "isTemplate": false,
    "count": 1,
    "lang": "hi",
    "updated": 0
  },
  {
    "id": "83d045d1-1695-4622-b39b-aa36f0e86f12",
    "data": [
      {
        "text": "नमस्ते",
        "userDefined": false
      }
    ],
    "isTemplate": false,
    "count": 3,
    "lang": "hi",
    "updated": 0
  },
  {
    "id": "acf9dff0-9888-4eb3-af30-b1074f420ad6",
    "data": [
      {
        "text": "क्या हाल है",
        "userDefined": false
      }
    ],
    "isTemplate": false,
    "count": 0,
    "lang": "hi",
    "updated": 0
  },
  {
    "id": "eb0d5670-a78d-47fc-9441-a7304ab2aebb",
    "data": [
      {
        "text": "सुनो, क्या हाल है",
        "userDefined": false
      }
    ],
    "isTemplate": false,
    "count": 0,
    "lang": "hi",
    "updated": 0
  },
  {
    "id": "60aeb79e-a43c-4a94-a520-e14f00e16617",
    "data": [
      {
        "text": "मेरी तरफ़ से नमस्ते",
        "userDefined": false
      }
    ],
    "isTemplate": false,
    "count": 0,
    "lang": "hi",
    "updated": 0
  }
]